{
  "currentVersion": "v5.0.0-alpha.5",
  "currentRelease": "Authenticated read-only Gmail connector",
  "currentScreenshotGroup": 24,
  "currentScreenshotGroupName": "Authenticated read-only Gmail connector and formal version alignment",
  "currentScreenshotGroupComplete": true,
  "v4SpineComplete": true,
  "connectorFoundationActive": true,
  "activeLocalConnectorFormats": [
    "CSV",
    "JSON",
    "ICS"
  ],
  "firstLiveReadOnlyConnector": "Google Calendar",
  "manualRefreshOnly": true,
  "maximumCalendarRefreshDays": 31,
  "reviewFirstIntake": true,
  "automaticExternalMutation": false,
  "automaticLifeOSMutation": false,
  "backgroundPolling": false,
  "emailRadarFoundationActive": true,
  "emailRadarEvidenceModes": [
    "Local JSON",
    "Local CSV"
  ],
  "mailboxConnected": false,
  "deterministicCandidateMatching": true,
  "candidateConfirmationRequired": true,
  "confirmedTimelineOnly": true,
  "verifiedTestResult": {
    "total": 80,
    "passed": 80,
    "failed": 0,
    "skipped": 0
  },
  "releaseBuild": "passed",
  "screenshotEvidenceComplete": true,
  "boundary": "Email Radar uses local/imported inert communication evidence only. No mailbox connection, send/write action, background scanning, AI interpretation, automatic follow-up, or automatic LifeOS state mutation is active.",
  "nextLane": "Return to Master Roadmap. Group 25 has not started.",
  "tag": "v5.0.0-alpha.5"
}
